{"nodes": [{"id": "d_my_life_system_nextcrm_app_main_actions_crm_audit_log_get_audit_log_by_entity_ts", "label": "get-audit-log-by-entity.ts", "file_type": "code", "source_file": "D:\\MY-LIFE-SYSTEM\\nextcrm-app-main\\actions\\crm\\audit-log\\get-audit-log-by-entity.ts", "source_location": "L1"}, {"id": "get_audit_log_by_entity_getauditlogbyentity", "label": "getAuditLogByEntity()", "file_type": "code", "source_file": "D:\\MY-LIFE-SYSTEM\\nextcrm-app-main\\actions\\crm\\audit-log\\get-audit-log-by-entity.ts", "source_location": "L4"}], "edges": [{"source": "d_my_life_system_nextcrm_app_main_actions_crm_audit_log_get_audit_log_by_entity_ts", "target": "prisma", "relation": "imports_from", "confidence": "EXTRACTED", "source_file": "D:\\MY-LIFE-SYSTEM\\nextcrm-app-main\\actions\\crm\\audit-log\\get-audit-log-by-entity.ts", "source_location": "L2", "weight": 1.0}, {"source": "d_my_life_system_nextcrm_app_main_actions_crm_audit_log_get_audit_log_by_entity_ts", "target": "get_audit_log_by_entity_getauditlogbyentity", "relation": "contains", "confidence": "EXTRACTED", "source_file": "D:\\MY-LIFE-SYSTEM\\nextcrm-app-main\\actions\\crm\\audit-log\\get-audit-log-by-entity.ts", "source_location": "L4", "weight": 1.0}], "raw_calls": [{"caller_nid": "get_audit_log_by_entity_getauditlogbyentity", "callee": "findMany", "source_file": "D:\\MY-LIFE-SYSTEM\\nextcrm-app-main\\actions\\crm\\audit-log\\get-audit-log-by-entity.ts", "source_location": "L11"}, {"caller_nid": "get_audit_log_by_entity_getauditlogbyentity", "callee": "slice", "source_file": "D:\\MY-LIFE-SYSTEM\\nextcrm-app-main\\actions\\crm\\audit-log\\get-audit-log-by-entity.ts", "source_location": "L22"}]}