{"nodes": [{"id": "d_my_life_system_nextcrm_app_main_tests_lib_email_crypto_test_ts", "label": "email-crypto.test.ts", "file_type": "code", "source_file": "D:\\MY-LIFE-SYSTEM\\nextcrm-app-main\\__tests__\\lib\\email-crypto.test.ts", "source_location": "L1"}], "edges": [{"source": "d_my_life_system_nextcrm_app_main_tests_lib_email_crypto_test_ts", "target": "email_crypto", "relation": "imports_from", "confidence": "EXTRACTED", "source_file": "D:\\MY-LIFE-SYSTEM\\nextcrm-app-main\\__tests__\\lib\\email-crypto.test.ts", "source_location": "L1", "weight": 1.0}], "raw_calls": []}